molo.globalsite-7.0.1-py2.7-nspkg.pth
molo/globalsite/__init__.py
molo/globalsite/geo.py
molo/globalsite/middleware.py
molo/globalsite/models.py
molo/globalsite/urls.py
molo/globalsite/views.py
molo/globalsite/wagtail_hooks.py
molo/globalsite/migrations/0001_initial.py
molo/globalsite/migrations/0002_globalsitesettings_show_country.py
molo/globalsite/migrations/__init__.py
molo/globalsite/templates/globalsite/country_site.html
molo/globalsite/tests/__init__.py
molo/globalsite/tests/test_views.py
molo.globalsite-7.0.1.dist-info/LICENSE
molo.globalsite-7.0.1.dist-info/METADATA
molo.globalsite-7.0.1.dist-info/WHEEL
molo.globalsite-7.0.1.dist-info/namespace_packages.txt
molo.globalsite-7.0.1.dist-info/top_level.txt
molo.globalsite-7.0.1.dist-info/RECORD
