Metadata-Version: 2.1
Name: molo.globalsite
Version: 7.0.1
Summary: Global site to be used with Molo.
Home-page: https://github.com/praekeltfoundation/molo.globalsite
Author: Praekelt.org
Author-email: dev@praekelt.org
License: BSD
Keywords: praekelt,mobi,web,django
Platform: UNKNOWN
Classifier: Programming Language :: Python
Classifier: Framework :: Django
Classifier: Topic :: Internet :: WWW/HTTP
Classifier: Topic :: Internet :: WWW/HTTP :: WSGI :: Application
Requires-Dist: molo.core (~=7.0.0)
Requires-Dist: geoip2
